setup.py
data_process/__init__.py
data_process/data_processor.py
json_data_process.egg-info/PKG-INFO
json_data_process.egg-info/SOURCES.txt
json_data_process.egg-info/dependency_links.txt
json_data_process.egg-info/top_level.txt